llama_index/llms/reka/__init__.py
llama_index/llms/reka/base.py
llama_index_llms_reka-0.3.1.dist-info/METADATA
llama_index_llms_reka-0.3.1.dist-info/WHEEL
llama_index_llms_reka-0.3.1.dist-info/licenses/LICENSE
llama_index_llms_reka-0.3.1.dist-info/RECORD
