Metadata-Version: 2.4
Name: llama-index-llms-reka
Version: 0.3.1
Summary: llama-index llms reka integration
Author-email: Alex Li <alexli@reka.ai>
License-Expression: MIT
License-File: LICENSE
Requires-Python: <4.0,>=3.9
Requires-Dist: llama-index-core<0.15,>=0.13.0
Requires-Dist: reka-api<4,>=3.0.8
